aivfs/__init__.py
aivfs/core/__init__.py
aivfs/core/exceptions.py
aivfs/core/fs.py
aivfs/core/fs_context.py
aivfs/core/fs_ops.py
aivfs/core/interfaces.py
aivfs/core/types.py
aivfs/metadata/__init__.py
aivfs/metadata/manager.py
aivfs-1.0.1.dist-info/LICENSE
aivfs-1.0.1.dist-info/METADATA
aivfs-1.0.1.dist-info/WHEEL
aivfs-1.0.1.dist-info/top_level.txt
aivfs-1.0.1.dist-info/RECORD
