Metadata-Version: 2.2
Name: aivfs
Version: 1.0.1
Summary: 一个AI虚拟文件系统
Author-email: LightJunction <lightjunction.me@gmail.com>
License: MIT
Project-URL: Homepage, https://github.com/LightJunction/AIVFS
Project-URL: Bug Tracker, https://github.com/LightJunction/AIVFS/issues
Classifier: Programming Language :: Python :: 3
Classifier: License :: OSI Approved :: MIT License
Classifier: Operating System :: OS Independent
Requires-Python: >=3.8
License-File: LICENSE
Requires-Dist: typing-extensions>=4.0.0
